{"chunk_definitions":[{"chunk_id":"cydehwoiormbl","chunk_label":"unnamed-chunk-1","document_id":"EBABE313","expansion_state":0,"options":{"cache":false,"echo":false,"engine":"r","include":false,"label":"unnamed-chunk-76"},"row":24,"row_count":1,"visible":true},{"chunk_id":"cxl2m0ojpsner","chunk_label":"unnamed-chunk-2","document_id":"EBABE313","expansion_state":0,"options":{"engine":"r","label":"unnamed-chunk-24","message":"F","warning":"F"},"row":38,"row_count":1,"visible":true},{"chunk_id":"c95k4pg4uqll1","chunk_label":"unnamed-chunk-3","document_id":"EBABE313","expansion_state":0,"options":{"engine":"r","label":"unnamed-chunk-97"},"row":58,"row_count":1,"visible":true},{"chunk_id":"cxd4l75v86eip","chunk_label":"unnamed-chunk-4","document_id":"EBABE313","expansion_state":0,"options":{"engine":"r","eval":"F","label":"unnamed-chunk-33"},"row":69,"row_count":1,"visible":true},{"chunk_id":"cscn4l42uhflz","chunk_label":"unnamed-chunk-5","document_id":"EBABE313","expansion_state":0,"options":{"echo":"F","engine":"r","label":"unnamed-chunk-34"},"row":73,"row_count":1,"visible":true},{"chunk_id":"cwpewws1yyp38","chunk_label":"unnamed-chunk-6","document_id":"EBABE313","expansion_state":0,"options":{"engine":"r","label":"unnamed-chunk-28"},"row":81,"row_count":1,"visible":true},{"chunk_id":"ci9v3rbm3ohcl","chunk_label":"unnamed-chunk-7","document_id":"EBABE313","expansion_state":0,"options":{"engine":"r","label":"unnamed-chunk-94"},"row":85,"row_count":1,"visible":true},{"chunk_id":"czn40dt7npb2j","chunk_label":"unnamed-chunk-8","document_id":"EBABE313","expansion_state":0,"options":{"echo":"F","engine":"r","label":"unnamed-chunk-37"},"row":98,"row_count":1,"visible":true},{"chunk_id":"cmwqd6zeop0xx","chunk_label":"unnamed-chunk-9","document_id":"EBABE313","expansion_state":0,"options":{"echo":"F","engine":"r","label":"unnamed-chunk-41"},"row":102,"row_count":1,"visible":true},{"chunk_id":"c72zte83pgsg8","chunk_label":"unnamed-chunk-10","document_id":"EBABE313","expansion_state":0,"options":{"engine":"r","label":"unnamed-chunk-99"},"row":107,"row_count":1,"visible":true},{"chunk_id":"cpsokb1qqzbmb","chunk_label":"unnamed-chunk-11","document_id":"EBABE313","expansion_state":0,"options":{"engine":"r","label":"unnamed-chunk-48"},"row":123,"row_count":1,"visible":true},{"chunk_id":"cympd05ixx10z","chunk_label":"unnamed-chunk-12","document_id":"EBABE313","expansion_state":0,"options":{"engine":"r","eval":"F","label":"unnamed-chunk-50"},"row":134,"row_count":1,"visible":true},{"chunk_id":"c750j1nhg1ga9","chunk_label":"unnamed-chunk-14","document_id":"EBABE313","expansion_state":0,"options":{"engine":"r","label":"unnamed-chunk-51"},"row":144,"row_count":1,"visible":true},{"chunk_id":"cfv8kbyyuw446","chunk_label":"unnamed-chunk-15","document_id":"EBABE313","expansion_state":0,"options":{"engine":"r","label":"unnamed-chunk-95"},"row":148,"row_count":1,"visible":true},{"chunk_id":"crec4duc8koxr","chunk_label":"unnamed-chunk-17","document_id":"EBABE313","expansion_state":0,"options":{"echo":"F","engine":"r","label":"unnamed-chunk-54"},"row":166,"row_count":1,"visible":true},{"chunk_id":"cx7ry22w6zn72","chunk_label":"unnamed-chunk-18","document_id":"EBABE313","expansion_state":0,"options":{"engine":"r","label":"unnamed-chunk-55"},"row":171,"row_count":1,"visible":true},{"chunk_id":"ca2zwrgr1ojr5","chunk_label":"unnamed-chunk-19","document_id":"EBABE313","expansion_state":0,"options":{"engine":"r","label":"unnamed-chunk-56"},"row":185,"row_count":1,"visible":true},{"chunk_id":"cq32p8qug1t6l","chunk_label":"unnamed-chunk-21","document_id":"EBABE313","expansion_state":0,"options":{"echo":"F","engine":"r","label":"unnamed-chunk-59"},"row":201,"row_count":1,"visible":true},{"chunk_id":"cy0aa7dk35huq","chunk_label":"unnamed-chunk-22","document_id":"EBABE313","expansion_state":0,"options":{"engine":"r","label":"unnamed-chunk-65"},"row":207,"row_count":1,"visible":true},{"chunk_id":"crm3mpgjy1p8o","chunk_label":"unnamed-chunk-23","document_id":"EBABE313","expansion_state":0,"options":{"engine":"r","label":"unnamed-chunk-96"},"row":211,"row_count":1,"visible":true},{"chunk_id":"ctfltefhliqmx","chunk_label":"unnamed-chunk-24","document_id":"EBABE313","expansion_state":0,"options":{"echo":"F","engine":"r","eval":"F","label":"unnamed-chunk-63"},"row":222,"row_count":1,"visible":true},{"chunk_id":"c7jrqrugip77a","chunk_label":"unnamed-chunk-26","document_id":"EBABE313","expansion_state":0,"options":{"engine":"r","label":"unnamed-chunk-64"},"row":231,"row_count":1,"visible":true},{"chunk_id":"cgpv0hwx25g5z","chunk_label":"unnamed-chunk-27","document_id":"EBABE313","expansion_state":0,"options":{"echo":"F","engine":"r","label":"unnamed-chunk-92","message":"F","warning":"F"},"row":275,"row_count":1,"visible":true}],"doc_write_time":1565236375}